[{
	"title": "Doctors",
	"subtitle": "Series 19: 137. Lamb Dopiaza Nights",
	"synopses":{
		"small":""
	},
	"images": {
		"standard": "https://ichef.bbci.co.uk/images/ic/832x468/p05sjj2q.jpg"
	},
	"labels": {
		"category": "BBC One",
		"editorial": ""
	},
	"versions": {
		"duration": "60"
	}
},{
	"title": "Doctors",
	"subtitle": "Series 19: 136. False Friend",
	"synopses":{
		"small": ""},
	"images": {
		"standard": "https://ichef.bbci.co.uk/images/ic/832x468/p05sjj23.jpg"
	},
	"labels": {
		"category": "BBC One",
		"editorial": ""
	},
	"versions": {
		"duration": "58"
	}
},
{
	"title": "Doctors",
	"subtitle": "Series 19: 135. Lullaby",
	"synopses":{
		"small": ""},
	"images": {
		"standard": "https://ichef.bbci.co.uk/images/ic/832x468/p05s9hjh.jpg"
	},
	"labels": {
		"category": "BBC One",
		"editorial": ""
	},
	"versions": {
		"duration": "58"
	}
},
{
	"title": "Doctors",
	"subtitle": "Series 19: 134. A Safe Place",
	"synopses":{
		"small": ""},
	"images": {
		"standard": "https://ichef.bbci.co.uk/images/ic/832x468/p05s9hj3.jpg"
	},
	"labels": {
		"category": "BBC One",
		"editorial": ""
	},
	"versions": {
		"duration": "60"
	}
},
{
	"title": "Doctors",
	"subtitle": "Series 19: 133. The Best Policy?",
	"editorial_subtitle": "",
	"synopses": {
		"small": ""
	},
	"images": {
		"standard": "https://ichef.bbci.co.uk/images/ic/832x468/p05st57k.jpg"
	},
	"labels": {
		"category": "BBC One",
		"editorial": ""
	},
	"versions": {
		"duration": "60 mins"
	}
},
{
	"title": "Doctors",
	"subtitle": "Series 19: 133. The Best Policy?",
	"synopses": {
		"small": ""
	},
	"images": {
		"standard": "https://ichef.bbci.co.uk/images/ic/832x468/p05s9hhw.jpg"
	},
	"labels": {
		"category": "BBC One",
		"editorial": ""
	},
	"versions": {
		"duration": "120 mins"
	}
},
{
	"title": "Doctors",
	"subtitle": "Series 19: 132. Blood, Sweat and Tears",
	"synopses": {
		"small": ""
	},
	"images": {
		"standard": "https://ichef.bbci.co.uk/images/ic/832x468/p05snlf8.jpg"
	},
	"labels": {
		"category": "BBC One",
		"editorial": ""
	},
	"versions": {
		"duration": "30 mins"
	}
},
{
	"title": "Doctors",
	"subtitle": "Series 19: 131. Risk Management",
	"synopses":{
		"small":""
	},
	"images": {
		"standard": "https://ichef.bbci.co.uk/images/ic/832x468/p05snlb2.jpg"
	},
	"labels": {
		"category": "BBC One",
		"editorial": ""
	},
	"versions": {
		"duration": "60"
	}
},
{
	"title": "Doctors",
	"subtitle": "Series 19: 130. Tinselitis",
	"synopses":{
		"small":""
	},
	"images": {
		"standard": "https://ichef.bbci.co.uk/images/ic/832x468/p05snl9q.jpg"
	},
	"labels": {
		"category": "BBC One",
		"editorial": ""
	},
	"versions": {
		"duration": "60"
	}
},
{
	"title": "Doctors",
	"subtitle": "Series 19: 129. Any Moment",
	"synopses":{
		"small":""
	},
	"images": {
		"standard": "https://ichef.bbci.co.uk/images/ic/832x468/p05snl9h.jpg"
	},
	"labels": {
		"category": "BBC One",
		"editorial": ""
	},
	"versions": {
		"duration": "60"
	}
},
{
	"title": "Doctors",
	"subtitle": "Series 19: 128. Twinkle Twinkle Video Star",
	"synopses":{
		"small":""
	},
	"images": {
		"standard": "https://ichef.bbci.co.uk/images/ic/832x468/p05q573s.jpg"
	},
	"labels": {
		"category": "BBC One",
		"editorial": ""
	},
	"versions": {
		"duration": "44"
	}
},
{
	"title": "Doctors",
	"subtitle": "Series 19: 127. No Room at the Inn",
	"synopses": {
		"small": ""
	},
	"images": {
		"standard": "https://ichef.bbci.co.uk/images/ic/832x468/p05q56z4.jpg"
	},
	"labels": {
		"category": "BBC One",
		"editorial": ""
	},
	"versions": {
		"duration": "57 mins"
	}
}]
